loquat/__init__.py
loquat/config.py
loquat/exception.py
loquat/handler.py
loquat/log.py
loquat/middleware.py
loquat/server.py
loquat/util.py
loquat/web.py
loquat-0.1.7.dist-info/LICENSE
loquat-0.1.7.dist-info/METADATA
loquat-0.1.7.dist-info/WHEEL
loquat-0.1.7.dist-info/top_level.txt
loquat-0.1.7.dist-info/RECORD
