Metadata-Version: 2.1
Name: loquat
Version: 0.1.7
Summary: A simple web framework based on Tornado.
Home-page: https://github.com/guanzhenxing/loquat
Author: Jesen Kwan
Author-email: guan.zhenxing@foxmail.com
License: MIT
Keywords: tornado,tornado-application,tornado-framework,tornado-web
Platform: UNKNOWN
Classifier: Development Status :: 5 - Production/Stable
Classifier: Programming Language :: Python :: 3
Classifier: Programming Language :: Python :: 3.5
Classifier: Programming Language :: Python :: 3.6
Classifier: Programming Language :: Python :: 3.7
Classifier: Programming Language :: Python :: 3.8
Classifier: Programming Language :: Python :: Implementation :: CPython
Classifier: Programming Language :: Python :: Implementation :: PyPy
Classifier: Intended Audience :: Developers
Classifier: License :: OSI Approved :: MIT License
Requires-Python: >=3.5.0
Requires-Dist: tornado
